openbio/__init__.py
openbio-0.1.0.dist-info/METADATA
openbio-0.1.0.dist-info/WHEEL
openbio-0.1.0.dist-info/entry_points.txt
openbio-0.1.0.dist-info/RECORD
