Metadata-Version: 2.4
Name: openbio
Version: 0.1.0
Summary: OpenBio - A placeholder package reserving the name for future development
Author-email: ravishar313 <ravishar313@gmail.com>
Requires-Python: >=3.8
